visualsort/__init__.py
visualsort/util/__init__.py
visualsort/util/module.py
visualsort-0.1.0.dist-info/licenses/LICENSE
visualsort-0.1.0.dist-info/METADATA
visualsort-0.1.0.dist-info/WHEEL
visualsort-0.1.0.dist-info/top_level.txt
visualsort-0.1.0.dist-info/RECORD
