Metadata-Version: 2.4
Name: visualsort
Version: 0.1.0
Summary: Visualsort lets you write sorting algorithms with given functions and then render them to videos.
Home-page: https://github.com/yourusername/my_package
Author: Tomas Bivainis
Author-email: Tomas Bivainis <bivainis.tomas@gmail.com>
License: MIT License
Project-URL: Homepage, https://github.com/TomasBivainis/visualsort
License-File: LICENSE
Requires-Dist: pillow
Requires-Dist: moviepy
Requires-Dist: numpy
Requires-Dist: pytest
Requires-Dist: pytest-mock
Requires-Dist: urllib3
Dynamic: author
Dynamic: home-page
Dynamic: license-file
